dl/Util.py
dl/__init__.py
dl/__version__.py
dl/authClient.py
dl/dltasks.py
dl/queryClient.py
dl/resClient.py
dl/specClient.py
dl/storeClient.py
dl/helpers/__init__.py
dl/helpers/all.py
dl/helpers/cluster.py
dl/helpers/crossmatch.py
dl/helpers/legacy.py
dl/helpers/plot.py
dl/helpers/utils.py
noaodatalab-2.20.0.data/scripts/datalab
noaodatalab-2.20.0.data/scripts/mountvofs
vos/BitVector.py
vos/CacheMetaData.py
vos/CadcCache.py
vos/NodeCache.py
vos/SharedLock.py
vos/__init__.py
vos/__version__.py
vos/cantop.py
vos/commonparser.py
vos/fuse.py
vos/html2text.py
vos/logExceptions.py
vos/md5_cache.py
vos/utils.py
vos/vofs.py
vos/vos.py
noaodatalab-2.20.0.dist-info/LICENSE
noaodatalab-2.20.0.dist-info/METADATA
noaodatalab-2.20.0.dist-info/WHEEL
noaodatalab-2.20.0.dist-info/top_level.txt
noaodatalab-2.20.0.dist-info/RECORD
